Metadata-Version: 2.4
Name: tc66c2mqtt
Version: 0.4.1
Summary: Sends MQTT events from TC66C device
Author-email: Jens Diemer <github@jensdiemer.de>
License: GPL-3.0-or-later
Project-URL: Documentation, https://github.com/jedie/tc66c2mqtt
Project-URL: Source, https://github.com/jedie/tc66c2mqtt
Requires-Python: >=3.11
Requires-Dist: ha-services>=2.5.0
Requires-Dist: pycryptodome
Requires-Dist: bleak
Requires-Dist: kaitaistruct
Requires-Dist: cli-base-utilities>=0.17.0
Requires-Dist: bx_py_utils
Requires-Dist: tyro
Requires-Dist: rich
